setup.py
znanija/__init__.py
znanija.egg-info/PKG-INFO
znanija.egg-info/SOURCES.txt
znanija.egg-info/dependency_links.txt
znanija.egg-info/not-zip-safe
znanija.egg-info/top_level.txt