Metadata-Version: 1.0
Name: znanija
Version: 0.1
Summary: Scrape znanija.com
Home-page: http://github.com/filalex77/znanija
Author: filalex77
Author-email: filalex77@gmail.com
License: MIT
Platform: UNKNOWN
